{"preference aggregation": "agregación de preferencias", "multiagent application": "aplicación multiagente", "voting theory": "teoría de votación", "banzhaf power index": "Índice de potencia de Banzhaf", "analysis of algorithm and problem complexity": "Análisis de algoritmo y complejidad de problemas", "algorithm and problem complexity analysis": "Análisis de algoritmo y complejidad de problemas", "social choice theory": "Teoría de la elección social", "automated agent voting": "Votación de agente automatizado", "network flow game": "Juego de flujo de red", "probabilistic model": "modelo probabilístico", "connectivity game": "juego de conectividad", "computational complexity": "complejidad computacional", "vote": "votar", "power index": "índice de energía"}