{"accumulating the logs as:(6)sl=1N∑t=1Nlogp(Ll|xt​, θ)": "acumulando los registros como: (6) sl = 1n∑t = 1nlogp (ll | xt, θ)", "assume that frames are independent and multiply the posterior estimates of the last layer": "Suponga que los marcos son independientes y multiplican las estimaciones posteriores de la última capa", "combine the evidence from past frames": "Combinar la evidencia de los marcos pasados", "DNN": "DNN", "DNNs": "DNNS", "evidence from past frames": "evidencia de marcos pasados", "i-vectors": "Vectores I", "multiplying the output probabilities pl obtained for all of its frames": "Multiplicar las probabilidades de salida PL obtenida para todos sus marcos", "other approaches": "Otros enfoques", "target languages": "Idiomas objetivo", "test utterance": "prueba de prueba"}