{"AM parts": "AM Piezas", "average porosity": "porosidad promedio", "build direction": "dirección de construcción", "characterization of surface roughness": "Caracterización de la rugosidad de la superficie", "characterize AM parts": "Caracterizar partes de AM", "comparison of the part to its design model": "Comparación de la parte con su modelo de diseño", "demonstrate a specific type of defect": "demostrar un tipo específico de defecto", "electron beam melted samples": "Muestras de haz de electrones derretidos", "electron beam raster and overlap pattern.": "Raster de haz de electrones y patrón de superposición.", "HIP": "CADERA", "Hot Isostatic Pressing": "Prensado isostático caliente", "microCT": "microct", "MicroCT": "Microct", "not follow the build direction": "no seguir la dirección de construcción", "porosity distribution": "distribución de porosidad", "porosity images": "Imágenes de porosidad", "porosity in AM components": "porosidad en los componentes AM", "porosity structure changes": "Cambios de la estructura de la porosidad", "porosity structures in parts": "Estructuras de porosidad en partes", "preliminary results": "resultados preliminares", "recent reports": "informes recientes", "very low average porosity levels": "niveles de porosidad promedio muy bajos", "visualization of defects": "Visualización de defectos"}